README
initd.py
setup.py
initd.egg-info/PKG-INFO
initd.egg-info/SOURCES.txt
initd.egg-info/dependency_links.txt
initd.egg-info/requires.txt
initd.egg-info/top_level.txt
test/test_initd.py